vptree/__init__.py
py_vptree-1.0.0.dist-info/LICENSE
py_vptree-1.0.0.dist-info/METADATA
py_vptree-1.0.0.dist-info/WHEEL
py_vptree-1.0.0.dist-info/RECORD
