Metadata-Version: 2.1
Name: py-vptree
Version: 1.0.0
Summary: A Python library to create vantage point trees (VP-trees)
License: MIT
Author: Nyeki.py
Author-email: hello@nyeki.dev
Requires-Python: >=3.6,<4.0
Classifier: License :: OSI Approved :: MIT License
Classifier: Programming Language :: Python :: 3
Classifier: Programming Language :: Python :: 3.6
Classifier: Programming Language :: Python :: 3.7
Classifier: Programming Language :: Python :: 3.8
Classifier: Programming Language :: Python :: 3.9
Classifier: Programming Language :: Python :: 3.10
Classifier: Programming Language :: Python :: 3.11
